pytest_zest/.gitkeep
pytest_zest/__init__.py
pytest_zest/hooks.py
pytest_zest-0.0.1.dist-info/entry_points.txt
pytest_zest-0.0.1.dist-info/LICENSE
pytest_zest-0.0.1.dist-info/WHEEL
pytest_zest-0.0.1.dist-info/METADATA
pytest_zest-0.0.1.dist-info/RECORD
