Metadata-Version: 2.1
Name: pytest-zest
Version: 0.0.1
Summary: Zesty additions to pytest.
Author: Indi Harrington
Author-email: indigoharrington@gmail.com
Requires-Python: >=3.10,<4.0
Classifier: Programming Language :: Python :: 3
Classifier: Programming Language :: Python :: 3.10
Classifier: Programming Language :: Python :: 3.11
